odoo/addons/stock_orderpoint_manual_procurement_uom/README.rst
odoo/addons/stock_orderpoint_manual_procurement_uom/__init__.py
odoo/addons/stock_orderpoint_manual_procurement_uom/__manifest__.py
odoo/addons/stock_orderpoint_manual_procurement_uom/i18n/stock_orderpoint_manual_procurement_uom.pot
odoo/addons/stock_orderpoint_manual_procurement_uom/models/__init__.py
odoo/addons/stock_orderpoint_manual_procurement_uom/models/stock_warehouse_orderpoint.py
odoo/addons/stock_orderpoint_manual_procurement_uom/static/description/icon.png
odoo/addons/stock_orderpoint_manual_procurement_uom/tests/__init__.py
odoo/addons/stock_orderpoint_manual_procurement_uom/tests/test_stock_orderpoint_manual_procurement.py
odoo/addons/stock_orderpoint_manual_procurement_uom/wizards/__init__.py
odoo/addons/stock_orderpoint_manual_procurement_uom/wizards/make_procurement_orderpoint.py
odoo11_addon_stock_orderpoint_manual_procurement_uom-11.0.1.0.0.99.dev2.dist-info/DESCRIPTION.rst
odoo11_addon_stock_orderpoint_manual_procurement_uom-11.0.1.0.0.99.dev2.dist-info/METADATA
odoo11_addon_stock_orderpoint_manual_procurement_uom-11.0.1.0.0.99.dev2.dist-info/RECORD
odoo11_addon_stock_orderpoint_manual_procurement_uom-11.0.1.0.0.99.dev2.dist-info/WHEEL
odoo11_addon_stock_orderpoint_manual_procurement_uom-11.0.1.0.0.99.dev2.dist-info/metadata.json
odoo11_addon_stock_orderpoint_manual_procurement_uom-11.0.1.0.0.99.dev2.dist-info/top_level.txt
