Metadata-Version: 2.0
Name: odoo11-addon-stock-orderpoint-manual-procurement-uom
Version: 11.0.1.0.0.99.dev2
Summary: Glue module for stock_orderpoint_uom and stock_orderpoint_manual_procurement
Home-page: https://github.com/OCA/stock-logistics-warehouse
Author: Eficent, Odoo Community Association (OCA)
Author-email: support@odoo-community.org
License: AGPL-3
Platform: UNKNOWN
Classifier: Programming Language :: Python
Classifier: Framework :: Odoo
Classifier: License :: OSI Approved :: GNU Affero General Public License v3
Requires-Python: >=2.7, !=3.0.*, !=3.1.*, !=3.2.*, !=3.3.*, !=3.4.*
Requires-Dist: odoo (<11.1dev,>=11.0a)
Requires-Dist: odoo11-addon-stock-orderpoint-manual-procurement
Requires-Dist: odoo11-addon-stock-orderpoint-uom
